LICENSE
MANIFEST.in
README.rst
pytest_resource.py
setup.py
pytest_resource.egg-info/PKG-INFO
pytest_resource.egg-info/SOURCES.txt
pytest_resource.egg-info/dependency_links.txt
pytest_resource.egg-info/entry_points.txt
pytest_resource.egg-info/requires.txt
pytest_resource.egg-info/top_level.txt