Metadata-Version: 1.2
Name: pytest-resource
Version: 0.1.3
Summary: Load resource fixture plugin to use with pytest
Home-page: https://github.com/kzmake/pytest-resource
Author: Kazuki Iwata
Author-email: kazu.0516.k0n0f@gmail.com
Maintainer: Kazuki Iwata
Maintainer-email: kazu.0516.k0n0f@gmail.com
License: MIT
Platform: UNKNOWN
Classifier: Development Status :: 4 - Beta
Classifier: Framework :: Pytest
Classifier: Intended Audience :: Developers
Classifier: Topic :: Software Development :: Testing
Classifier: Programming Language :: Python
Classifier: Programming Language :: Python :: 3
Classifier: Programming Language :: Python :: 3.4
Classifier: Programming Language :: Python :: 3.5
Classifier: Programming Language :: Python :: 3.6
Classifier: Programming Language :: Python :: Implementation :: CPython
Classifier: Programming Language :: Python :: Implementation :: PyPy
Classifier: Operating System :: OS Independent
Classifier: License :: OSI Approved :: MIT License
Requires-Python: >=2.7, !=3.0.*, !=3.1.*, !=3.2.*, !=3.3.*
